{
  "name": "הלכה",
  "content_type": "סימן",
  "subcategories": [
    {
      "name": "ארבע טורים",
      "content_type": "סימן",
      "books": {
        "טור אורח חיים": { "pages": 697 },
        "טור יורה דעה": { "pages": 403 },
        "טור אבן העזר": { "pages": 178 },
        "טור חושן משפט": { "pages": 427 }
      }
    },
    {
      "name": "שולחן ערוך",
      "content_type": "סימן",
      "books": {
        "שולחן ערוך אורח חיים": { "pages": 697 },
        "שולחן ערוך יורה דעה": { "pages": 403 },
        "שולחן ערוך אבן העזר": { "pages": 178 },
        "שולחן ערוך חושן משפט": { "pages": 427 }
      }
    },
    {
      "name": "משנה ברורה",
      "content_type": "סימן",
      "books": {
        "משנה ברורה חלק א": { "pages": 124 },
        "משנה ברורה חלק ב": { "pages": 117 },
        "משנה ברורה חלק ג": { "pages": 103 },
        "משנה ברורה חלק ד": { "pages": 84 },
        "משנה ברורה חלק ה": { "pages": 101 },
        "משנה ברורה חלק ו": { "pages": 167 }
      }
    }
  ]
}
