{
    "name": "משנה תורה",
    "content_type": "פרק",
    "columns": ["מצב"],
    "data": {
        "ספר המדע": {
            "pages": 10
        },
        "ספר אהבה": {
            "pages": 15
        },
        "ספר זמנים": {
            "pages": 30
        },
        "ספר נשים": {
            "pages": 25
        },
        "ספר קדושה": {
            "pages": 17
        },
        "ספר הפלאה": {
            "pages": 13
        },
        "ספר זרעים": {
            "pages": 17
        },
        "ספר עבודה": {
            "pages": 9
        },
        "ספר הקרבנות": {
            "pages": 10
        },
        "ספר טהרה": {
            "pages": 13
        },
        "ספר נזיקין": {
            "pages": 14
        },
        "ספר קניין": {
            "pages": 29
        },
        "ספר משפטים": {
            "pages": 27
        },
        "ספר שופטים": {
            "pages": 26
        }
    },
    "last_updated": "2025-06-08T00:44:16.938035"
}